pybran/__init__.py
pybran/decorators.py
pybran/exceptions.py
pybran/loaders.py
pybran/serializers.py
pybran/synchronized.py
pybran-0.1.2.dist-info/LICENSE
pybran-0.1.2.dist-info/METADATA
pybran-0.1.2.dist-info/WHEEL
pybran-0.1.2.dist-info/top_level.txt
pybran-0.1.2.dist-info/RECORD
