Metadata-Version: 2.1
Name: pybran
Version: 0.1.2
Summary: A simple binary serialization/deserialization library for Python
Home-page: https://github.com/nannafudge/bran
Author: nannafudge
Author-email: toastnoodles@gmail.com
License: UNKNOWN
Project-URL: Bug Tracker, https://github.com/nannafudge/bran/issues
Platform: UNKNOWN
Classifier: Programming Language :: Python :: 3
Classifier: License :: OSI Approved :: MIT License
Classifier: Operating System :: OS Independent
Requires-Python: >=3.6
License-File: LICENSE
Provides-Extra: test
Requires-Dist: pytest ; extra == 'test'
Requires-Dist: pylint ; extra == 'test'
Requires-Dist: coverage ; extra == 'test'
Requires-Dist: bandit ; extra == 'test'
